allianceauth/__init__.py
allianceauth/apps.py
allianceauth/checks.py
allianceauth/context_processors.py
allianceauth/hooks.py
allianceauth/middleware.py
allianceauth/models.py
allianceauth/urls.py
allianceauth/views.py
allianceauth/analytics/__init__.py
allianceauth/analytics/admin.py
allianceauth/analytics/apps.py
allianceauth/analytics/models.py
allianceauth/analytics/tasks.py
allianceauth/analytics/utils.py
allianceauth/analytics/fixtures/disable_analytics.json
allianceauth/analytics/migrations/0001_initial.py
allianceauth/analytics/migrations/0002_add_AA_Team_Token.py
allianceauth/analytics/migrations/0003_Generate_Identifier.py
allianceauth/analytics/migrations/0004_auto_20211015_0502.py
allianceauth/analytics/migrations/0005_alter_analyticspath_ignore_path.py
allianceauth/analytics/migrations/0006_more_ignore_paths.py
allianceauth/analytics/migrations/0007_analyticstokens_secret.py
allianceauth/analytics/migrations/0008_add_AA_GA-4_Team_Token .py
allianceauth/analytics/migrations/0009_remove_analyticstokens_ignore_paths_and_more.py
allianceauth/analytics/migrations/0010_alter_analyticsidentifier_options.py
allianceauth/analytics/migrations/__init__.py
allianceauth/analytics/tests/__init__.py
allianceauth/analytics/tests/test_models.py
allianceauth/analytics/tests/test_tasks.py
allianceauth/analytics/tests/test_utils.py
allianceauth/authentication/__init__.py
allianceauth/authentication/admin.py
allianceauth/authentication/app_settings.py
allianceauth/authentication/apps.py
allianceauth/authentication/auth_hooks.py
allianceauth/authentication/backends.py
allianceauth/authentication/checks.py
allianceauth/authentication/constants.py
allianceauth/authentication/decorators.py
allianceauth/authentication/forms.py
allianceauth/authentication/hmac_urls.py
allianceauth/authentication/managers.py
allianceauth/authentication/middleware.py
allianceauth/authentication/models.py
allianceauth/authentication/signals.py
allianceauth/authentication/tasks.py
allianceauth-4.12.0.dist-info/entry_points.txt
allianceauth-4.12.0.dist-info/licenses/LICENSE
allianceauth-4.12.0.dist-info/WHEEL
allianceauth-4.12.0.dist-info/METADATA
allianceauth-4.12.0.dist-info/RECORD
