Metadata-Version: 2.4
Name: allianceauth
Version: 4.12.0
Summary: An auth system for EVE Online to help in-game organizations
Keywords: allianceauth,eveonline
Author-email: Alliance Auth <adarnof@gmail.com>
Requires-Python: >=3.8,<3.13
Classifier: Environment :: Web Environment
Classifier: Framework :: Celery
Classifier: Framework :: Django
Classifier: Framework :: Django :: 4.2
Classifier: Intended Audience :: Developers
Classifier: License :: OSI Approved :: GNU General Public License v2 (GPLv2)
Classifier: Operating System :: POSIX :: Linux
Classifier: Programming Language :: Python
Classifier: Programming Language :: Python :: 3 :: Only
Classifier: Programming Language :: Python :: 3.8
Classifier: Programming Language :: Python :: 3.9
Classifier: Programming Language :: Python :: 3.10
Classifier: Programming Language :: Python :: 3.11
Classifier: Programming Language :: Python :: 3.12
Classifier: Topic :: Internet :: WWW/HTTP
Classifier: Topic :: Internet :: WWW/HTTP :: Dynamic Content
License-File: LICENSE
Requires-Dist: bcrypt<5
Requires-Dist: beautifulsoup4
Requires-Dist: celery>=5.2,<6
Requires-Dist: celery-once>=3.0.1
Requires-Dist: django>=4.2,<5
Requires-Dist: django-bootstrap-form
Requires-Dist: django-bootstrap5>=23.3
Requires-Dist: django-celery-beat>=2.3
Requires-Dist: django-esi>=7.0.1
Requires-Dist: django-redis>=5.2
Requires-Dist: django-registration>=3.3,<3.4
Requires-Dist: django-solo
Requires-Dist: django-sortedm2m
Requires-Dist: django-sri
Requires-Dist: dnspython
Requires-Dist: mysqlclient>=2.1
Requires-Dist: openfire-restapi
Requires-Dist: packaging>=21
Requires-Dist: passlib
Requires-Dist: pydiscourse
Requires-Dist: python-slugify>=1.2
Requires-Dist: pyyaml
Requires-Dist: redis>=4
Requires-Dist: requests>=2.9.1
Requires-Dist: requests-oauthlib
Requires-Dist: semantic-version
Requires-Dist: slixmpp<1.9
Requires-Dist: ua-parser
Requires-Dist: user-agents
Requires-Dist: myst-parser ; extra == "docs"
Requires-Dist: sphinx ; extra == "docs"
Requires-Dist: sphinx-copybutton ; extra == "docs"
Requires-Dist: sphinx-rtd-theme>=2,<3 ; extra == "docs"
Requires-Dist: sphinx-tabs ; extra == "docs"
Requires-Dist: sphinxcontrib-django ; extra == "docs"
Requires-Dist: coverage>=4.3.1 ; extra == "test"
Requires-Dist: django-webtest ; extra == "test"
Requires-Dist: requests-mock>=1.2 ; extra == "test"
Project-URL: Documentation, https://allianceauth.readthedocs.io/
Project-URL: Homepage, https://gitlab.com/allianceauth/allianceauth
Project-URL: Source, https://gitlab.com/allianceauth/allianceauth
Project-URL: Tracker, https://gitlab.com/allianceauth/allianceauth/-/issues
Provides-Extra: docs
Provides-Extra: test
